README.md
setup.py
bucket_list/__init__.py
s3_bucket_list.egg-info/PKG-INFO
s3_bucket_list.egg-info/SOURCES.txt
s3_bucket_list.egg-info/dependency_links.txt
s3_bucket_list.egg-info/entry_points.txt
s3_bucket_list.egg-info/requires.txt
s3_bucket_list.egg-info/top_level.txt