Metadata-Version: 1.0
Name: s3-bucket-list
Version: 1.1.dev0
Summary: CLI to query AWS S3 buckets through CloudWatch metrics
Home-page: http://github.com/Moshe-Immerman/bucket-list
Author: Moshe Immerman
Author-email: name.surname@gmail.com
License: BSD
Platform: any
